{
  "id": 9,
  "stageName": "Chapter_09: 巨大な石柱",
  "difficulty": "7x7",
  "prologue": "戦場の中心、崩落した大地から巨大な石柱がせり出した。\n其れは天を突く救済の標か。あるいは地を貫く終焉の杭か。\n絶望的な沈黙の中、石柱は膨大な情報を放ち始める。",
  "words": [
    {
      "id": "w9-1", "size": 7,
      "pattern": [
        [0,0,0,1,0,0,0],
        [0,0,0,1,0,0,0],
        [0,0,0,1,0,0,0],
        [1,1,1,1,1,1,1],
        [0,0,0,1,0,0,0],
        [0,0,0,1,0,0,0],
        [0,0,0,1,0,0,0]
      ],
      "light": { "ans": "神殿", "text": "「其は、至高の＿＿なり」（天を仰ぐ聖なる尖塔）" },
      "dark": { "ans": "墓標", "text": "「其は、永劫の＿＿なり」（一族を葬る巨大な指標）" },
      "trueSide": { "ans": "記録", "text": "「其は、膨大な＿＿なり」（情報を保持する集積回路）" }
    }
  ],
  "epilogue": "見上げる空は遠く、足元の土はあまりに脆い。\n私たちはただ、其処に在る巨大な意志に圧倒されていた。"
}
