{
  "id": 5,
  "stageName": "Chapter_05: 抜かれた刃",
  "difficulty": "3x3",
  "prologue": "沈黙の終わりを告げるように、一振りの鋼が抜かれた。冷たい金属音が戦場に響き渡る。\n交差する意志の中で、私たちは互いに叫んだ。",
  "words": [
    {
      "id": "w5-1", "size": 3, "pattern": [[0,0,1],
      									   [0,1,0],
      									   [1,0,0]],
      "light": { "ans": "断絶", "text": "「＿すべし」（邪悪なる影を切り裂く）" },
      "dark": { "ans": "守護", "text": "「＿すべし」（共に生きる明日を繋ぐ）" },
      "trueSide": { "ans": "結合", "text": "「＿すべし」（交差する存在の点）" }
    },
    {
      "id": "w5-2", "size": 3, "pattern": [[1,1,1],
      									   [0,1,0],
      									   [0,1,0]],
      "light": { "ans": "罪", "text": "「其れは、＿なり」（天の秩序を乱す不浄）" },
      "dark": { "ans": "罰", "text": "「其れは、＿なり」（孤独に抗えぬ我らの宿命）" },
      "trueSide": { "ans": "理", "text": "「其れは、＿なり」（重なり合う事象の端）" }
    }
  ],
  "epilogue": "刃を向けたことが罪なのか、共に在ろうとしたことが罰なのか。\n吹き抜ける風だけが、赤く染まりゆく大地の声を聴いていた。"
}
